{
  "account_id": "1",
  "data_type": "scan_data",
  "timestamp": "2025-10-01T23:12:13.423463",
  "data": {
    "current_chat": "专 / 专转",
    "current_chat_id": -1001832527222,
    "chat_id": -1002544959919,
    "status": "completed",
    "total_chats": 174,
    "current_index": 13,
    "completed": 44,
    "skipped": 0,
    "errors": 0,
    "total_messages": 2,
    "scanned_chats": [
      {
        "id": -1002127424462,
        "title": "专转 砖专转 住爪 砖转",
        "status": "completed",
        "messages_found": 0,
        "error": null,
        "skipped_reason": null
      },
      {
        "id": -1001692212602,
        "title": "住拽住 砖专 2024",
        "status": "completed",
        "messages_found": 0,
        "error": null,
        "skipped_reason": null
      },
      {
        "id": -1001344573395,
        "title": "住拽住 专转  !",
        "status": "completed",
        "messages_found": 0,
        "error": null,
        "skipped_reason": null
      },
      {
        "id": -1001258862444,
        "title": "Girl Boy il 住专 砖专 ",
        "status": "completed",
        "messages_found": 0,
        "error": null,
        "skipped_reason": null
      },
      {
        "id": -1001757858757,
        "title": " 砖专 专转",
        "status": "completed",
        "messages_found": 0,
        "error": null,
        "skipped_reason": null
      },
      {
        "id": -1002282499461,
        "title": "砖   || 住爪",
        "status": "completed",
        "messages_found": 1,
        "error": null,
        "skipped_reason": null
      },
      {
        "id": -1002657525227,
        "title": "专转 砖 转 ",
        "status": "completed",
        "messages_found": 0,
        "error": null,
        "skipped_reason": null
      },
      {
        "id": -1002642584963,
        "title": "专拽 专转 住拽住",
        "status": "completed",
        "messages_found": 0,
        "error": null,
        "skipped_reason": null
      },
      {
        "id": -1001439617993,
        "title": "驻 转 专转",
        "status": "completed",
        "messages_found": 0,
        "error": null,
        "skipped_reason": null
      },
      {
        "id": -1002898656788,
        "title": "Open your mouth  XXL Cocks",
        "status": "completed",
        "messages_found": 0,
        "error": null,
        "skipped_reason": null
      },
      {
        "id": -1001333488188,
        "title": "爪 注专",
        "status": "completed",
        "messages_found": 0,
        "error": null,
        "skipped_reason": null
      },
      {
        "id": -1002557279382,
        "title": "拽爪转 专转",
        "status": "completed",
        "messages_found": 1,
        "error": null,
        "skipped_reason": null
      },
      {
        "id": -1001768427006,
        "title": "漏| 住驻 |",
        "status": "completed",
        "messages_found": 0,
        "error": null,
        "skipped_reason": null
      },
      {
        "id": -1001444468254,
        "title": "住抓 转",
        "status": "completed",
        "messages_found": 0,
        "error": null,
        "skipped_reason": null
      },
      {
        "id": -1001832527222,
        "title": " 砖专 gay 住抓 转",
        "status": "completed",
        "messages_found": 0,
        "error": null,
        "skipped_reason": null
      },
      {
        "id": -1002602980351,
        "title": "专 专 18+",
        "status": "completed",
        "messages_found": 0,
        "error": null,
        "skipped_reason": null
      },
      {
        "id": -1001239682653,
        "title": "拽专住转",
        "status": "completed",
        "messages_found": 0,
        "error": null,
        "skipped_reason": null
      },
      {
        "id": -1002030880695,
        "title": " 拽 拽专转 转 专拽",
        "status": "completed",
        "messages_found": 0,
        "error": null,
        "skipped_reason": null
      },
      {
        "id": -1001684740037,
        "title": "プ转 专砖",
        "status": "completed",
        "messages_found": 0,
        "error": null,
        "skipped_reason": null
      },
      {
        "id": -1002544959919,
        "title": "专 / 专转",
        "status": "completed",
        "messages_found": 0,
        "error": null,
        "skipped_reason": null
      }
    ],
    "messages_found": 0,
    "progress_percent": 6
  },
  "hash": "30ae1809d5c08367b30ff869acfa6b8d"
}